create_flask_application/cmdl.py
create_flask_application/create_flask_application.py
create_flask_application/templates/__init__.py
create_flask_application/templates/deploy.jinja-sh
create_flask_application/templates/gitignore.jinja
create_flask_application/templates/prod-wsgi.jinja-ini
create_flask_application/templates/requirements.jinja-txt
create_flask_application/templates/alembic/alembic.jinja-ini
create_flask_application/templates/alembic/env.py
create_flask_application/templates/flask/run_wsgi.jinja-py
create_flask_application/templates/flask/app/__init__.jinja-py
create_flask_application/templates/flask/app/auth.jinja-py
create_flask_application/templates/flask/app/exc.jinja-py
create_flask_application/templates/flask/app/io.jinja-py
create_flask_application/templates/flask/app/mail.jinja-py
create_flask_application/templates/flask/app/models.jinja-py
create_flask_application/templates/flask/app/utils.jinja-py
create_flask_application/templates/flask/app/config/config.prod.jinja-yaml
create_flask_application/templates/flask/app/events/controllers.jinja-py
create_flask_application/templates/flask/app/events/event_utils.jinja-py
create_flask_application/templates/flask/app/events/schema.jinja-py
create_flask_application/templates/flask/app/rest/controllers.jinja-py
create_flask_application/templates/flask/app/rest/schema.jinja-py
create_flask_application/templates/flask/app/templates/endpoint_doc.rst-jinja
create_flask_application/templates/flask/app/templates/event_doc.rst-jinja
create_flask_application/templates/sphinx/conf.py_t
create_flask_application/templates/sphinx/master_doc.rst_t
create_flask_application-0.1.9.dist-info/LICENSE
create_flask_application-0.1.9.dist-info/METADATA
create_flask_application-0.1.9.dist-info/WHEEL
create_flask_application-0.1.9.dist-info/entry_points.txt
create_flask_application-0.1.9.dist-info/top_level.txt
create_flask_application-0.1.9.dist-info/RECORD
