Metadata-Version: 2.1
Name: create-flask-application
Version: 0.1.9
Summary: This is an application designed to speed up process of configuring evironment for new flask RESTful projects.
Home-page: UNKNOWN
Author: igoras1993
Author-email: igor.kantorski@gmail.com
License: GPLv3
Keywords: flask create generate
Platform: UNKNOWN
Classifier: Development Status :: 3 - Alpha
Classifier: Environment :: Console
Classifier: Framework :: Flask
Classifier: Intended Audience :: Developers
Classifier: License :: OSI Approved :: GNU General Public License v3 (GPLv3)
Classifier: Operating System :: Microsoft
Classifier: Operating System :: POSIX :: Linux
Classifier: Programming Language :: Python :: 3 :: Only
Classifier: Topic :: Software Development :: Code Generators
Classifier: Topic :: Utilities
Requires-Dist: jinja2
